jupyterfs/__init__.py
jupyterfs/auth.py
jupyterfs/browser-test.js
jupyterfs/browser_check.py
jupyterfs/config.py
jupyterfs/extension.py
jupyterfs/fs_wrapper.py
jupyterfs/metamanager.py
jupyterfs/pathutils.py
jupyterfs/snippets.py
jupyterfs/contents_managers/__init__.py
jupyterfs/contents_managers/absolute.py
jupyterfs/labextension/build_log.json
jupyterfs/labextension/package.json
jupyterfs/labextension/schemas/jupyter-fs/package.json.orig
jupyterfs/labextension/schemas/jupyter-fs/plugin.json
jupyterfs/labextension/static/lib_index_js.5cd4a54bc0763bcd3aee.js
jupyterfs/labextension/static/lib_index_js.5cd4a54bc0763bcd3aee.js.map
jupyterfs/labextension/static/node_modules_pnpm_file-saver_2_0_5_node_modules_file-saver_dist_FileSaver_min_js.03295131795da7dccb10.js
jupyterfs/labextension/static/node_modules_pnpm_file-saver_2_0_5_node_modules_file-saver_dist_FileSaver_min_js.03295131795da7dccb10.js.map
jupyterfs/labextension/static/remoteEntry.5aa25c1830a13edd45b1.js
jupyterfs/labextension/static/remoteEntry.5aa25c1830a13edd45b1.js.map
jupyterfs/labextension/static/style.js
jupyterfs/labextension/static/style_index_js-data_image_svg_xml_base64_PHN2ZyB4bWxucz0iaHR0cDovL3d3dy53My5vcmcvMjAwMC9zdmci-f8082c.b8382be1280200f7bba0.js
jupyterfs/labextension/static/style_index_js-data_image_svg_xml_base64_PHN2ZyB4bWxucz0iaHR0cDovL3d3dy53My5vcmcvMjAwMC9zdmci-f8082c.b8382be1280200f7bba0.js.map
jupyterfs/labextension/static/vendors-node_modules_pnpm_css-loader_6_11_0_webpack_5_98_0_node_modules_css-loader_dist_cjs_j-13cc56.605636aeae51457dc6fd.js
jupyterfs/labextension/static/vendors-node_modules_pnpm_css-loader_6_11_0_webpack_5_98_0_node_modules_css-loader_dist_cjs_j-13cc56.605636aeae51457dc6fd.js.map
jupyterfs/labextension/static/vendors-node_modules_pnpm_material-ui_core_4_12_4__types_react_18_3_18_react-dom_18_3_1_react-14338c.1993141451e1e9d6d1f8.js
jupyter_fs-1.1.0.dist-info/METADATA
jupyter_fs-1.1.0.dist-info/WHEEL
jupyter_fs-1.1.0.dist-info/licenses/AUTHORS
jupyter_fs-1.1.0.dist-info/licenses/LICENSE
jupyter_fs-1.1.0.dist-info/RECORD
