Metadata-Version: 2.4
Name: jupyter-fs
Version: 1.1.0
Summary: A Filesystem-like mult-contents manager backend for Jupyter
Project-URL: Repository, https://github.com/jpmorganchase/jupyter-fs
Project-URL: Homepage, https://github.com/jpmorganchase/jupyter-fs
Author-email: the jupyter-fs authors <t.paine154@gmail.com>
License: Apache-2.0
License-File: AUTHORS
License-File: LICENSE
Keywords: Extensions,Filesystem,Filetree,IPython,Jupyter,JupyterLab,Tree
Classifier: Development Status :: 4 - Beta
Classifier: Framework :: Jupyter
Classifier: Framework :: Jupyter :: JupyterLab
Classifier: License :: OSI Approved :: Apache Software License
Classifier: Programming Language :: Python
Classifier: Programming Language :: Python :: 3
Classifier: Programming Language :: Python :: 3.9
Classifier: Programming Language :: Python :: 3.10
Classifier: Programming Language :: Python :: 3.11
Classifier: Programming Language :: Python :: 3.12
Classifier: Programming Language :: Python :: 3.13
Classifier: Programming Language :: Python :: Implementation :: CPython
Classifier: Programming Language :: Python :: Implementation :: PyPy
Requires-Python: >=3.9
Requires-Dist: jupyter-server<3,>=2
Requires-Dist: jupyterlab<5,>=4
Provides-Extra: develop
Requires-Dist: boto3; extra == 'develop'
Requires-Dist: build; extra == 'develop'
Requires-Dist: bump-my-version; extra == 'develop'
Requires-Dist: check-manifest; extra == 'develop'
Requires-Dist: fs-miniofs; extra == 'develop'
Requires-Dist: fs-s3fs>=1.1.1; extra == 'develop'
Requires-Dist: fs-smbfs>=0.6.3; extra == 'develop'
Requires-Dist: fs>=2.4.11; extra == 'develop'
Requires-Dist: fsspec>=2023.6.0; extra == 'develop'
Requires-Dist: hatch-jupyter-builder; extra == 'develop'
Requires-Dist: hatchling; extra == 'develop'
Requires-Dist: jupyterlab<5,>=4; extra == 'develop'
Requires-Dist: pysmb; extra == 'develop'
Requires-Dist: pytest; extra == 'develop'
Requires-Dist: pytest-asyncio; extra == 'develop'
Requires-Dist: pytest-cov; extra == 'develop'
Requires-Dist: pytest-jupyter[server]; extra == 'develop'
Requires-Dist: pytest-sugar; extra == 'develop'
Requires-Dist: pytest-xdist; extra == 'develop'
Requires-Dist: ruff<0.12,>=0.9; extra == 'develop'
Requires-Dist: s3fs>=2024; extra == 'develop'
Requires-Dist: smbprotocol; extra == 'develop'
Requires-Dist: twine; extra == 'develop'
Requires-Dist: wheel; extra == 'develop'
Provides-Extra: fs
Requires-Dist: fs-s3fs>=1.1.1; extra == 'fs'
Requires-Dist: fs-smbfs>=0.6.3; extra == 'fs'
Requires-Dist: fs>=2.4.11; extra == 'fs'
Provides-Extra: fsspec
Requires-Dist: fsspec>=2023.6.0; extra == 'fsspec'
